ab/__init__.py
ab/abdb.py
ab/actions.py
ab/agent_io.py
ab/atoms.py
ab/awareness.py
ab/benchmark.py
ab/card_utils.py
ab/checkpoint.py
ab/claude_mem_bridge.py
ab/code_dna.py
ab/comparators.py
ab/debug.py
ab/decay.py
ab/embeddings.py
ab/energy.py
ab/genesis.py
ab/genetics.py
ab/hardware.py
ab/mind.py
ab/models.py
ab/moment_ledger.py
ab/narrator.py
ab/neural.py
ab/neural_memory.py
ab/overlord.py
ab/recall.py
ab/rfs_recall.py
ab/search.py
ab/self_agent.py
ab/skills.py
ab/subselves.py
ab/tasker_net.py
ab/transforms.py
ab/tree_web.py
ab/vector_search.py
supe/__init__.py
supe/cli.py
supe/mcp_server.py
supe/sensory.py
supe/subselves.py
supe/supe.py
tasc/__init__.py
tasc/ab_integration.py
tasc/ab_storage.py
tasc/atom.py
tasc/atomtypes.py
tasc/cli.py
tasc/dna_atoms.py
tasc/domains.py
tasc/evidence.py
tasc/q_manager.py
tasc/reasoning_engine.py
tasc/relation_storage.py
tasc/relations.py
tasc/self_validation.py
tasc/tasc.py
tasc/tasc_queue.py
tasc/tui.py
tasc/u2.py
tasc/ulist.py
tasc/uobj.py
tasc/validation.py
tasc/validation_integration.py
tasc/varint.py
tascer/__init__.py
tascer/ab_storage.py
tascer/action_registry.py
tascer/actions.yaml
tascer/agent_session.py
tascer/approval.py
tascer/checkpoint.py
tascer/claude_planner.py
tascer/cli.py
tascer/contracts.py
tascer/llm_planner.py
tascer/llm_proof.py
tascer/report.py
tascer/runner.py
tascer/sdk_wrapper.py
tascer/abilities/__init__.py
tascer/abilities/base.py
tascer/abilities/web_scraper.py
tascer/actions/__init__.py
tascer/actions/base.py
tascer/actions/executor.py
tascer/actions/format.py
tascer/actions/lint.py
tascer/actions/patch.py
tascer/actions/registry.py
tascer/actions/test.py
tascer/audit/__init__.py
tascer/audit/markdown.py
tascer/boosters/__init__.py
tascer/boosters/repro_bundle.py
tascer/boosters/safety.py
tascer/gates/__init__.py
tascer/gates/confidence_gate.py
tascer/gates/evolution_gate.py
tascer/gates/exit_code.py
tascer/gates/experiment_gate.py
tascer/gates/file_gate.py
tascer/gates/gap_gate.py
supe-0.1.1.dist-info/METADATA
supe-0.1.1.dist-info/WHEEL
supe-0.1.1.dist-info/entry_points.txt
supe-0.1.1.dist-info/licenses/LICENSE
supe-0.1.1.dist-info/RECORD
