Metadata-Version: 2.4
Name: supe
Version: 0.1.1
Summary: Cognitive memory for AI agents with validation and proof-of-work
Project-URL: Homepage, https://github.com/xayhemLLC/supe
Project-URL: Repository, https://github.com/xayhemLLC/supe
Project-URL: Issues, https://github.com/xayhemLLC/supe/issues
License: MIT
License-File: LICENSE
Keywords: agents,ai,cognitive,memory,proof-of-work,validation
Classifier: Development Status :: 3 - Alpha
Classifier: Intended Audience :: Developers
Classifier: License :: OSI Approved :: MIT License
Classifier: Programming Language :: Python :: 3
Classifier: Programming Language :: Python :: 3.10
Classifier: Programming Language :: Python :: 3.11
Classifier: Programming Language :: Python :: 3.12
Classifier: Topic :: Scientific/Engineering :: Artificial Intelligence
Requires-Python: >=3.10
Requires-Dist: click>=8.0
Requires-Dist: numpy>=1.24
Requires-Dist: pyyaml>=6.0
Requires-Dist: rich>=13.0
Provides-Extra: anthropic
Requires-Dist: anthropic>=0.30; extra == 'anthropic'
Provides-Extra: dev
Requires-Dist: anthropic>=0.30; extra == 'dev'
Requires-Dist: pyinstaller>=6.0; extra == 'dev'
Requires-Dist: pytest-asyncio>=0.23; extra == 'dev'
Requires-Dist: pytest-cov>=4.0; extra == 'dev'
Requires-Dist: pytest>=7.0; extra == 'dev'
Requires-Dist: ruff>=0.1; extra == 'dev'
Provides-Extra: docs
Requires-Dist: mkdocs-material>=9.0; extra == 'docs'
Requires-Dist: mkdocs>=1.5; extra == 'docs'
Requires-Dist: mkdocstrings[python]>=0.24; extra == 'docs'
